http_api_lambda/__init__.py
http_api_lambda/app.py
http_api_lambda/core.py
http_api_lambda/exceptions.py
http_api_lambda/models.py
http_api_lambda/router.py
http_api_lambda-0.0.3.dist-info/METADATA
http_api_lambda-0.0.3.dist-info/WHEEL
http_api_lambda-0.0.3.dist-info/licenses/LICENSE
http_api_lambda-0.0.3.dist-info/RECORD
